Workbook

Sheet README
A1: Microeconomics of Stem-Cell Manufacturing: Earth vs Low Earth Orbit
A2: Question: What is the first product that will be fundamentally cheaper to make in microgravity, and at what launch, manufacturing and return costs is it viable?
A3: Built 24 Oct 2026. Currency: USD, price year 2026 (source prices from other years are NOT inflation-adjusted).
A4: Three scenarios, same formulas: CMV_* = SPACE VIABILITY CASE (heart muscle cells on an autonomous free-flyer with projected launch/return prices; every bet flagged). CM_* = heart muscle cells with today's ISS logistics. HSC_* = cord-blood blood stem cells.
A5: The calculator reads these same values (app/scenario_data.js is generated by build_spreadsheet.py).
A7: How to use
A8: 1. Edit BLUE cells on *_Assumptions (Low / Most likely / High). Black cells are formulas; green cells link to another sheet.
A9: 2. *_Earth and *_Space build cost per batch and good cells per batch from the 'Most likely' column.
A10: 3. *_Comparison answers the question: cost per unit, and the maximum launch price, return cost and orbital manufacturing cost at which space still matches Earth.
A11: 4. *_Probabilities lists key claims with the author's subjective probability they are true. Discussion aids only; they do not feed the model.
A12: 5. PRD_Check reproduces the specification's worked example to prove the formulas.
A13: 6. To push changes into the calculator, edit build_spreadsheet.py and rerun it (editing the xlsx alone does not update the app).
... A18: Key finding: Earth's best 3D bioreactors already reach ~88-94% correct heart cells, so a pure purity gain is capped near 1.06-1.14x. The thesis needs MORE correct cells per input cell (r_g), which is supported only by simulated-microgravity data so far.

Sheet CMV_Assumptions
A1: Space viability case: heart muscle cells on an autonomous free-flyer (projection): assumptions. Point estimate = Most likely. Blue = input, black = formula.
A2: Low/High = range found in (or judged from) the evidence. Subjective confidence = author's probability the true value lies in [Low, High]; not used by the model.
A4: ID | B4: Parameter | C4: Unit | D4: Side | E4: Low | F4: Most likely (point) | G4: High | H4: Distribution | I4: Evidence status | J4: Evidence strength | K4: Source IDs | L4: Basis / derivation | M4: Limitations | N4: Subjective confidence range holds | O4: Used directly by calculator?
A5: U | B5: Cells per reporting unit | C5: cells/unit | D5: Both | E5: 1000000 | F5: 1000000 | G5: 1000000 | H5: fixed | I5: definition | J5: n/a | L5: 1 unit = 1 million correct, working heart muscle cells (cTnT+ cardiomyocytes passing release). A clinical dose is ~50-150 units (C11). | M5: Accounting choice only. | O5: yes
A6: N0 | B6: Input iPSCs per differentiation batch | C6: cells | D6: Both | E6: 1000000000 | F6: 1000000000 | G6: 1000000000 | H6: fixed | I6: measured in target system (derived) | J6: Strong | K6: C12 | L6: Industrial batch scale: ~1e9 input iPSCs gives ~2.5e9 CMs (C3 ratio); Ncardia reports 7.5e9-cell batches (C12). | M6: Assumes an orbital bioreactor can run the same batch size, which has NOT been demonstrated (favors space). | N6: 0.5 | O6: yes
A7: g_E | B7: Earth: total cells out per input iPSC (expansion during differentiation) | C7: fold | D7: Earth | E7: 1.5 | F7: 2.8 | G7: 4 | H7: triangular | I7: measured in target system (derived) | J7: Strong | K7: C3, C2 | L7: ~2.5 CMs per input iPSC at ~90% purity -> ~2.8 total cells per input (C3). Range is judgment around that. | M7: Derived; per-protocol variation large. | N7: 0.6 | O7: yes
A8: q_E | B8: Earth: share of output that is correct heart muscle cells (purity) | C8: fraction | D8: Earth | E8: 0.58 | F8: 0.88 | G8: 0.94 | H8: triangular | I8: measured in target system | J8: Strong | K8: C1, C2, C3, C12 | L8: Bioreactor purity: 58% mean for one iPSC line (C1, low); ~87-90% typical (C3, C12); 93.5% best (C2, high). | M8: Earth's best 3D process already near 90%+, so there is little room for a purity gain. | N8: 0.8 | O8: yes
A9: p_E | B9: Earth: chance a batch succeeds and is released | C9: probability | D9: Earth | E9: 0.75 | F9: 0.85 | G9: 0.95 | H9: triangular | I9: measured in target system | J9: Strong | K9: C4, C1 | L9: '>85% purity in over 80% of runs' (C4); all 3 runs from batch-expanded cells failed in C1. | M9: No published GMP lot-release rate for iPSC-CMs. | N9: 0.6 | O9: yes
A10: E_cells | B10: Earth: starting iPSCs (master cell bank vial) | C10: USD/batch | D10: Earth | E10: 1000 | F10: 5000 | G10: 10000 | H10: triangular | I10: measured in target system | J10: Strong | K10: C5 | L10: GMP iPSC bank vial ~$1,000-10,000 (C5). | M10: Excludes $3M+ process development and bank creation costs. | N10: 0.7 | O10: yes
A11: E_consumables | B11: Earth: media, growth factors, single-use plastics | C11: USD/batch | D11: Earth | E11: 10000 | F11: 40000 | G11: 120000 | H11: triangular | I11: engineering estimate (derived) | J11: Weak | K11: C3 | L11: Research-grade materials ~$569 per 124M CMs (C3) -> ~$11k for ~2.5e9 CMs; GMP-grade media assumed 2-10x higher. | M11: GMP multiplier is judgment. | N11: 0.5 | O11: yes
A12: E_labor | B12: Earth: GMP labor | C12: USD/batch | D12: Earth | E12: 50000 | F12: 120000 | G12: 250000 | H12: triangular | I12: engineering estimate | J12: Weak | K12: C5 | L12: Labor is ~50% of hPSC manufacturing cost (C5); sized roughly equal to all other per-batch costs. | M12: Derived share, not a measured per-batch figure. | N12: 0.5 | O12: yes
A13: E_facility | B13: Earth: GMP clean-room allocation | C13: USD/batch | D13: Earth | E13: 44000 | F13: 73000 | G13: 110000 | H13: triangular | I13: engineering estimate (derived) | J13: Weak | K13: C5 | L13: Facility upkeep ~$2.2M/yr (C5) / 20-50 batches per year. | M13: Batches/year is judgment. | N13: 0.55 | O13: yes
A14: E_equipment | B14: Earth: bioreactor and equipment allocation | C14: USD/batch | D14: Earth | E14: 5000 | F14: 15000 | G14: 40000 | H14: triangular | I14: engineering estimate | J14: Weak | L14: Stirred-tank bioreactor system amortized over batches. Author estimate. | M14: No source extracted. | N14: 0.4 | O14: yes
A15: E_qc | B15: Earth: release testing | C15: USD/batch | D15: Earth | E15: 10000 | F15: 20000 | G15: 50000 | H15: triangular | I15: measured in target system | J15: Strong | K15: C5 | L15: Outsourced testing ~$10k per lot (C5); more assays for a final cell product. | N15: 0.6 | O15: yes
A16: E_other | B16: Earth: other production cost | C16: USD/batch | D16: Earth | E16: 0 | F16: 0 | G16: 0 | H16: fixed | I16: not extracted | J16: n/a | L16: All costs itemized above. | O16: yes
A17: E_delivery | B17: Earth: delivery cost | C17: USD/batch | D17: Earth | E17: 0 | F17: 0 | G17: 0 | H17: fixed | I17: not extracted | J17: n/a | L17: Not modeled. Earth shipping losses also not modeled. | M17: Slightly favors Earth. | O17: yes
A18: r_g | B18: Space vs Earth: total cells out per input iPSC | C18: ratio | D18: Space | E18: 1.5 | F18: 3 | G18: 4 | H18: triangular | I18: measured in another system | J18: Moderate | K18: C6, C7 | L18: Upper half of the simulated-microgravity evidence: 1.5-4x more heart cells per input stem cell vs 3D at 1g (C6); strong proliferation on ISS (C7). Mode 3.0 = midpoint of C6's range. | M18: BET: real-flight yield per input cell not yet published. Today's broader range is 0.8-4 (CM scenario). | N18: 0.35 | O18: yes
A19: r_q | B19: Space vs Earth: share of correct heart cells (purity ratio) - THESIS LEVER | C19: ratio | D19: Space | E19: 1 | F19: 1.05 | G19: 1.06 | H19: triangular | I19: measured in another system | J19: Moderate | K19: C6 | L19: Near the 100%-purity ceiling: ~99% purity reported in simulated microgravity (C6). | M19: Small effect by construction: Earth purity already ~88%. | N19: 0.4 | O19: yes
A20: s | B20: Space: share of good cells surviving return, storage, thaw | C20: fraction | D20: Space | E20: 0.5 | F20: 0.75 | G20: 0.97 | H20: triangular | I20: measured in another system | J20: Moderate | K20: S17, S18, C8 | L20: Post-thaw recovery of cryopreserved stem cells ~68-98% (S17, S18); low 0.5 allows for re-entry stress. | M20: CD34+ data used as proxy; Earth product cryo losses not modeled (favors Earth). | N20: 0.5 | O20: yes
A21: p_S | B21: Space: chance a batch succeeds and is released | C21: probability | D21: Space | E21: 0.7 | F21: 0.85 | G21: 0.95 | H21: triangular | I21: projection | J21: Projection (future bet) | L21: Mature, repeated autonomous flights (assumed). | M21: BET: no orbital GMP batch history. | N21: 0.3 | O21: yes
A22: S_cells | B22: Space: starting iPSCs | C22: USD/batch | D22: Space | E22: 1000 | F22: 5000 | G22: 10000 | H22: triangular | I22: measured in target system | J22: Strong | K22: C5 | L22: Same as Earth. | M22: Sampled independently of Earth. | N22: 0.7 | O22: yes
A23: S_consumables | B23: Space: media and consumables flown | C23: USD/batch | D23: Space | E23: 10000 | F23: 40000 | G23: 120000 | H23: triangular | I23: engineering estimate (derived) | J23: Weak | K23: C3 | L23: Same as Earth. | M23: Sampled independently of Earth. | N23: 0.5 | O23: yes
A24: crew_hours | B24: Space: crew time per batch | C24: hours/batch | D24: Space | E24: 0 | F24: 0 | G24: 0 | H24: fixed | I24: projection | J24: Projection (future bet) | K24: P2 | L24: Autonomous free-flyer (Varda-style): no astronaut time. | N24: 0.6 | O24: via derived row
A25: crew_rate | B25: Space: ISS crew time price | C25: USD/hour | D25: Space | E25: 130000 | F25: 130000 | G25: 130000 | H25: fixed | I25: measured in target system (price) | J25: Strong | K25: S9 | L25: NASA 2021 full-value commercial pricing. | M25: Policy price; NASA may discount research. | N25: 0.8 | O25: via derived row
A26: S_labor | B26: Space: crew and operations time | C26: USD/batch | D26: Space | E26: 10000 | F26: 30000 | G26: 80000 | H26: triangular | I26: projection | J26: Projection (future bet) | K26: P2 | L26: Ground operations team monitoring an autonomous free-flyer instead of ISS crew time. | M26: BET: no published operations cost. | N26: 0.4 | O26: yes
A27: S_facility | B27: Space: orbital lab fee / implementation partner | C27: USD/batch | D27: Space | E27: 30000 | F27: 80000 | G27: 200000 | H27: triangular | I27: projection | J27: Projection (future bet) | K27: P2 | L27: Per-batch share of a free-flyer platform (bus, power, thermal) flown many times. | M27: BET: no published price. | N27: 0.3 | O27: yes
A28: S_equipment | B28: Space: flight bioreactor allocation | C28: USD/batch | D28: Space | E28: 10000 | F28: 40000 | G28: 120000 | H28: triangular | I28: projection | J28: Projection (future bet) | L28: Reusable flight bioreactor amortized over many flights. | M28: BET: placeholder. | N28: 0.3 | O28: yes
A29: S_qc | B29: Space: release testing | C29: USD/batch | D29: Space | E29: 10000 | F29: 20000 | G29: 50000 | H29: triangular | I29: measured in target system | J29: Strong | K29: C5 | L29: Same as Earth. | N29: 0.6 | O29: yes
A30: S_other | B30: Space: ground GMP work (pre-flight expansion, post-return processing) | C30: USD/batch | D30: Space | E30: 60000 | F30: 150000 | G30: 300000 | H30: triangular | I30: engineering estimate | J30: Weak | K30: C5 | L30: Ground team still expands iPSCs before flight and processes cells after return (labor + facility share). | M30: Judgment based on Earth labor/facility lines. | N30: 0.45 | O30: yes
A31: L | B31: Launch price to orbital lab | C31: USD/kg | D31: Space | E31: 200 | F31: 1000 | G31: 6500 | H31: triangular | I31: projection | J31: Projection (future bet) | K31: P1, S10 | L31: Low: Starship target ~$100-200/kg (aspirational, P1); mode: $1,000/kg = top of 'realistic mid-decade' range (P1); high: today's rideshare $6,500/kg (S10). | M31: BET: Starship has no published commercial price. | N31: 0.45 | O31: yes
A32: M | B32: Launched mass per batch (hardware share, media, packaging) | C32: kg/batch | D32: Space | E32: 10 | F32: 25 | G32: 60 | H32: triangular | I32: engineering estimate | J32: Weak | L32: ~1e9 iPSCs need ~1 L culture plus several litres of differentiation media over ~2 weeks, plus hardware share. Author estimate. | M32: SPECULATIVE. | N32: 0.4 | O32: yes
A33: ret_mass | B33: Return mass per batch incl. cold stowage | C33: kg/batch | D33: Space | E33: 5 | F33: 5 | G33: 5 | H33: fixed | I33: engineering estimate | J33: Weak | L33: Not used: return priced per capsule share below. | O33: via derived row
A34: down_rate | B34: Downmass price | C34: USD/kg | D34: Space | E34: 40000 | F34: 40000 | G34: 40000 | H34: fixed | I34: measured in target system (price) | J34: Strong | K34: S9 | L34: NASA 2021 full-value downmass price. | M34: Policy price. | N34: 0.8 | O34: via derived row
A35: C_return | B35: Return and recovery cost | C35: USD/batch | D35: Space | E35: 50000 | F35: 100000 | G35: 250000 | H35: triangular | I35: projection | J35: Projection (future bet) | K35: P2 | L35: ~$5M per reentry capsule flight (P2) shared by ~20-100 batches (50 at the mode). | M35: BET: batches per capsule assumed; capsule capacity not published. | N35: 0.35 | O35: yes
A36: C_other_del | B36: Other space delivery cost | C36: USD/batch | D36: Space | E36: 0 | F36: 0 | G36: 0 | H36: fixed | I36: not extracted | J36: n/a | L36: Not modeled separately. | O36: yes

Sheet CMV_Earth
A1: Space viability case: heart muscle cells on an autonomous free-flyer (projection) - Earth: cost and output per attempted batch (point estimates)
A3: Line item | B3: Value | C3: Unit | D3: Note
A4: Earth: starting iPSCs (master cell bank vial) | B4: =CMV_Assumptions!$F$10 | C4: USD/batch | D4: measured in target system
A5: Earth: media, growth factors, single-use plastics | B5: =CMV_Assumptions!$F$11 | C5: USD/batch | D5: engineering estimate (derived)
A6: Earth: GMP labor | B6: =CMV_Assumptions!$F$12 | C6: USD/batch | D6: engineering estimate
A7: Earth: GMP clean-room allocation | B7: =CMV_Assumptions!$F$13 | C7: USD/batch | D7: engineering estimate (derived)
A8: Earth: bioreactor and equipment allocation | B8: =CMV_Assumptions!$F$14 | C8: USD/batch | D8: engineering estimate
A9: Earth: release testing | B9: =CMV_Assumptions!$F$15 | C9: USD/batch | D9: measured in target system
A10: Earth: other production cost | B10: =CMV_Assumptions!$F$16 | C10: USD/batch | D10: not extracted
A11: C_E_prod: production cost per batch | B11: =SUM(B4:B10) | C11: USD/batch
A12: Earth delivery cost | B12: =CMV_Assumptions!$F$17 | C12: USD/batch
A13: C_E_del: delivered cost per batch | B13: =B11+B12 | C13: USD/batch
A15: N0: starting cells | B15: =CMV_Assumptions!$F$6 | C15: cells
A16: g_E: growth (cells out per starting cell) | B16: =CMV_Assumptions!$F$7 | C16: fold
A17: q_E: share of correct / qualified cells | B17: =CMV_Assumptions!$F$8 | C17: fraction
A18: p_E: batch success probability | B18: =CMV_Assumptions!$F$9 | C18: probability
A19: U: cells per unit | B19: =CMV_Assumptions!$F$5 | C19: cells/unit
A20: Y_E = N0 x g_E x q_E / U (successful batch) | B20: =B15*B16*B17/B19 | C20: units/batch
A21: Q_E = p_E x Y_E (expected per attempted batch) | B21: =B18*B20 | C21: units/batch
A22: c_E_prod: production cost per unit | B22: =IF(B21>0,B11/B21,"No usable output") | C22: USD/unit
A23: c_E: delivered cost per unit | B23: =IF(B21>0,B13/B21,"No usable output") | C23: USD/unit

Sheet CMV_Space
A1: Space viability case: heart muscle cells on an autonomous free-flyer (projection) - Space (LEO): cost and output per attempted batch (point estimates)
A3: Line item | B3: Value | C3: Unit | D3: Note
A4: Space: starting iPSCs | B4: =CMV_Assumptions!$F$22 | C4: USD/batch | D4: measured in target system
A5: Space: media and consumables flown | B5: =CMV_Assumptions!$F$23 | C5: USD/batch | D5: engineering estimate (derived)
A6: Space: crew and operations time | B6: =CMV_Assumptions!$F$26 | C6: USD/batch | D6: projection
A7: Space: orbital lab fee / implementation partner | B7: =CMV_Assumptions!$F$27 | C7: USD/batch | D7: projection
A8: Space: flight bioreactor allocation | B8: =CMV_Assumptions!$F$28 | C8: USD/batch | D8: projection
A9: Space: release testing | B9: =CMV_Assumptions!$F$29 | C9: USD/batch | D9: measured in target system
A10: Space: ground GMP work (pre-flight expansion, post-return processing) | B10: =CMV_Assumptions!$F$30 | C10: USD/batch | D10: engineering estimate
A11: C_S_prod: production (orbital manufacturing) cost per batch | B11: =SUM(B4:B10) | C11: USD/batch
A12: L: launch price | B12: =CMV_Assumptions!$F$31 | C12: USD/kg
A13: M: launched mass | B13: =CMV_Assumptions!$F$32 | C13: kg/batch
A14: C_launch = L x M | B14: =B12*B13 | C14: USD/batch
A15: Return and recovery (return mass x downmass price) | B15: =CMV_Assumptions!$F$35 | C15: USD/batch
A16: Other delivery | B16: =CMV_Assumptions!$F$36 | C16: USD/batch
A17: C_S_del: delivered cost per batch | B17: =B11+B14+B15+B16 | C17: USD/batch
A19: N0: starting cells (paired with Earth) | B19: =CMV_Assumptions!$F$6 | C19: cells
A20: g_E: Earth growth | B20: =CMV_Assumptions!$F$7 | C20: fold
A21: r_g: space/Earth growth ratio | B21: =CMV_Assumptions!$F$18 | C21: ratio
A22: g_S = g_E x r_g | B22: =B20*B21 | C22: fold
A23: q_E: Earth share of correct cells | B23: =CMV_Assumptions!$F$8 | C23: fraction
A24: r_q: space/Earth purity ratio (thesis lever) | B24: =CMV_Assumptions!$F$19 | C24: ratio
A25: q_S = q_E x r_q | B25: =B23*B24 | C25: fraction
A26: s: post-return retention | B26: =CMV_Assumptions!$F$20 | C26: fraction
A27: p_S: batch success probability | B27: =CMV_Assumptions!$F$21 | C27: probability
A28: U: cells per unit | B28: =CMV_Assumptions!$F$5 | C28: cells/unit
A29: Y_S_pre = N0 x g_S x q_S / U | B29: =B19*B22*B25/B28 | C29: units/batch
A30: Y_S = Y_S_pre x s | B30: =B29*B26 | C30: units/batch
A31: Q_S_pre = p_S x Y_S_pre | B31: =B27*B29 | C31: units/batch
A32: Q_S = p_S x Y_S (expected delivered per attempted batch) | B32: =B27*B30 | C32: units/batch
A33: c_S_prod: production cost per unit (before transport/return losses) | B33: =IF(B31>0,B11/B31,"No usable output") | C33: USD/unit
A34: c_S: delivered cost per unit | B34: =IF(B32>0,B17/B32,"No usable output") | C34: USD/unit

Sheet CMV_Comparison
A1: Space viability case: heart muscle cells on an autonomous free-flyer (projection) - comparison and viability (deterministic, point estimates)
A3: Metric | B3: Value | C3: Unit | D3: Note
A4: Earth delivered cost per unit (c_E) | B4: =CMV_Earth!B23 | C4: USD/unit
A5: Space delivered cost per unit (c_S) | B5: =CMV_Space!B34 | C5: USD/unit
A6: Space production cost per unit (c_S_prod) | B6: =CMV_Space!B33 | C6: USD/unit | D6: Includes orbital facility costs; NOT proof of a microgravity effect.
A7: Relative delivered savings = 1 - c_S/c_E | B7: =IF(AND(ISNUMBER(B4),ISNUMBER(B5),B4>0),1-B5/B4,"Not defined") | D7: Negative = space more expensive.
A8: Verdict | B8: =IF(AND(ISNUMBER(B4),ISNUMBER(B5)),IF(B5<B4,"Space cheaper","Earth cheaper or equal"),"See no-output flags")
A10: AT WHAT COSTS IS IT VIABLE? (each line changes one input, others held at point estimates)
A11: Max total space spend per batch to match Earth = c_E x Q_S | B11: =IFERROR(B4*CMV_Space!B32,"Not defined") | C11: USD/batch
A12: Max launch price L_max = (c_E x Q_S - C_S_prod - C_return - C_other) / M | B12: =IF(CMV_Space!B13>0,(B4*CMV_Space!B32-CMV_Space!B11-CMV_Space!B15-CMV_Space!B16)/CMV_Space!B13,"Not applicable (M=0)") | C12: USD/kg | D12: Negative = not competitive even with free launch.
A13: Max return cost per batch | B13: =IFERROR(B11-CMV_Space!B11-CMV_Space!B14-CMV_Space!B16,"Not defined") | C13: USD/batch | D13: Negative = not viable even with free return.
A14: Max orbital manufacturing cost per batch (C_S_prod) | B14: =IFERROR(B11-CMV_Space!B14-CMV_Space!B15-CMV_Space!B16,"Not defined") | C14: USD/batch | D14: Negative = not viable even with free manufacturing.
A15: Break-even growth ratio r_g_min = C_S_del x U / (c_E x p_S x N0 x g_E x q_S x s) | B15: =IFERROR(CMV_Space!B17*CMV_Space!B28/(B4*CMV_Space!B27*CMV_Space!B19*CMV_Space!B20*CMV_Space!B25*CMV_Space!B26),"Not defined") | C15: ratio
A16: Break-even purity ratio r_q_min = C_S_del x U / (c_E x p_S x N0 x g_S x q_E x s) | B16: =IFERROR(CMV_Space!B17*CMV_Space!B28/(B4*CMV_Space!B27*CMV_Space!B19*CMV_Space!B22*CMV_Space!B23*CMV_Space!B26),"Not defined") | C16: ratio | D16: Thesis lever.
A17: Maximum possible purity ratio = 1 / q_E (space purity capped at 100%) | B17: =IFERROR(1/CMV_Space!B23,"Not defined") | C17: ratio
A18: Can the purity advantage alone make space viable? | B18: =IF(AND(ISNUMBER(B16),ISNUMBER(B17)),IF(B16<=B17,"Possible in principle","NO: required ratio exceeds the 100%-purity cap"),"Not defined")
A19: Space cost per unit if 100% of space cells were correct | B19: =IFERROR(CMV_Space!B17/(CMV_Space!B27*CMV_Space!B19*CMV_Space!B22*CMV_Space!B26/CMV_Space!B28),"Not defined") | C19: USD/unit | D19: Best case for the thesis.
A20: Required output ratio C_S_del / C_E_del (Q_S/Q_E must exceed this) | B20: =IFERROR(CMV_Space!B17/CMV_Earth!B13,"Not defined") | C20: ratio
A21: Current output ratio Q_S / Q_E | B21: =IFERROR(CMV_Space!B32/CMV_Earth!B21,"Not defined") | C21: ratio
A23: P(r_g > r_g_min) under the triangular r_g range, all else fixed | B23: =IF(ISNUMBER(B15),IF(B15<=CMV_Assumptions!$E$18,1,IF(B15>=CMV_Assumptions!$G$18,0,IF(B15<=CMV_Assumptions!$F$18,1-(B15-CMV_Assumptions!$E$18)^2/((CMV_Assumptions!$G$18-CMV_Assumptions!$E$18)*(CMV_Assumptions!$F$18-CMV_Assumptions!$E$18)),(CMV_Assumptions!$G$18-B15)^2/((CMV_Assumptions!$G$18-CMV_Assumptions!$E$18)*(CMV_Assumptions!$G$18-CMV_Assumptions!$F$18))))),"Not defined") | C23: probability | D23: Analytic triangular tail. Conditional on the range; not a forecast. Joint uncertainty: run the calculator's Monte Carlo.

Sheet CMV_Probabilities
A1: Space viability case: heart muscle cells on an autonomous free-flyer (projection) - key assumptions and the author's subjective probability each is true
A2: Subjective judgments drafted from the evidence inventory for discussion; review and replace with your own. NOT derived from p-values, NOT used in the simulation, NOT independent of one another.
A4: ID | B4: Claim | C4: Subjective P(true) | D4: Evidence for | E4: Evidence against | F4: Comment
A5: B1 | B5: Real microgravity gives ~3x more correct heart cells per input stem cell than the best Earth 3D bioreactor | C5: 0.25 | D5: C6 (1.5-4x, simulated microgravity), C7 (ISS proliferation) | E5: C9, C10 (differentiation suppressed) | F5: The single biggest bet. Test it on the next flight.
A6: B2 | B6: Launch to LEO falls to ~$1,000/kg or less for small biotech payloads by the early 2030s | C6: 0.5 | D6: P1 | F6: Starship price unpublished.
A7: B3 | B7: An autonomous free-flyer can run a GMP cell-differentiation batch without crew | C7: 0.35 | D7: P2 (autonomous capsules fly today) | F7: No cell-therapy batch has flown this way.
A8: B4 | B8: A reentry capsule flight (~$5M) can be shared by ~50 batches | C8: 0.3 | D8: P2 | F8: Requires high demand and capsule capacity.
A9: B5 | B9: Space-made cells pass the same release tests after re-entry (same quality as Earth cells) | C9: 0.45 | D9: C8 (CM structure unchanged) | E9: C13 (radiation) | F9: Equivalence must be shown, not assumed.
A11: Product of all P IF independent (they are not; illustration only) | B11: =PRODUCT(C5:C9)
A12: Model-based P(r_g > break-even), from CMV_Comparison | B12: =CMV_Comparison!B23

Sheet CM_Assumptions
A1: Team thesis: iPSC-derived heart muscle cells (cardiomyocytes): assumptions. Point estimate = Most likely. Blue = input, black = formula.
A2: Low/High = range found in (or judged from) the evidence. Subjective confidence = author's probability the true value lies in [Low, High]; not used by the model.
A4: ID | B4: Parameter | C4: Unit | D4: Side | E4: Low | F4: Most likely (point) | G4: High | H4: Distribution | I4: Evidence status | J4: Evidence strength | K4: Source IDs | L4: Basis / derivation | M4: Limitations | N4: Subjective confidence range holds | O4: Used directly by calculator?
A5: U | B5: Cells per reporting unit | C5: cells/unit | D5: Both | E5: 1000000 | F5: 1000000 | G5: 1000000 | H5: fixed | I5: definition | J5: n/a | L5: 1 unit = 1 million correct, working heart muscle cells (cTnT+ cardiomyocytes passing release). A clinical dose is ~50-150 units (C11). | M5: Accounting choice only. | O5: yes
A6: N0 | B6: Input iPSCs per differentiation batch | C6: cells | D6: Both | E6: 1000000000 | F6: 1000000000 | G6: 1000000000 | H6: fixed | I6: measured in target system (derived) | J6: Strong | K6: C12 | L6: Industrial batch scale: ~1e9 input iPSCs gives ~2.5e9 CMs (C3 ratio); Ncardia reports 7.5e9-cell batches (C12). | M6: Assumes an orbital bioreactor can run the same batch size, which has NOT been demonstrated (favors space). | N6: 0.5 | O6: yes
A7: g_E | B7: Earth: total cells out per input iPSC (expansion during differentiation) | C7: fold | D7: Earth | E7: 1.5 | F7: 2.8 | G7: 4 | H7: triangular | I7: measured in target system (derived) | J7: Strong | K7: C3, C2 | L7: ~2.5 CMs per input iPSC at ~90% purity -> ~2.8 total cells per input (C3). Range is judgment around that. | M7: Derived; per-protocol variation large. | N7: 0.6 | O7: yes
A8: q_E | B8: Earth: share of output that is correct heart muscle cells (purity) | C8: fraction | D8: Earth | E8: 0.58 | F8: 0.88 | G8: 0.94 | H8: triangular | I8: measured in target system | J8: Strong | K8: C1, C2, C3, C12 | L8: Bioreactor purity: 58% mean for one iPSC line (C1, low); ~87-90% typical (C3, C12); 93.5% best (C2, high). | M8: Earth's best 3D process already near 90%+, so there is little room for a purity gain. | N8: 0.8 | O8: yes
A9: p_E | B9: Earth: chance a batch succeeds and is released | C9: probability | D9: Earth | E9: 0.75 | F9: 0.85 | G9: 0.95 | H9: triangular | I9: measured in target system | J9: Strong | K9: C4, C1 | L9: '>85% purity in over 80% of runs' (C4); all 3 runs from batch-expanded cells failed in C1. | M9: No published GMP lot-release rate for iPSC-CMs. | N9: 0.6 | O9: yes
A10: E_cells | B10: Earth: starting iPSCs (master cell bank vial) | C10: USD/batch | D10: Earth | E10: 1000 | F10: 5000 | G10: 10000 | H10: triangular | I10: measured in target system | J10: Strong | K10: C5 | L10: GMP iPSC bank vial ~$1,000-10,000 (C5). | M10: Excludes $3M+ process development and bank creation costs. | N10: 0.7 | O10: yes
A11: E_consumables | B11: Earth: media, growth factors, single-use plastics | C11: USD/batch | D11: Earth | E11: 10000 | F11: 40000 | G11: 120000 | H11: triangular | I11: engineering estimate (derived) | J11: Weak | K11: C3 | L11: Research-grade materials ~$569 per 124M CMs (C3) -> ~$11k for ~2.5e9 CMs; GMP-grade media assumed 2-10x higher. | M11: GMP multiplier is judgment. | N11: 0.5 | O11: yes
A12: E_labor | B12: Earth: GMP labor | C12: USD/batch | D12: Earth | E12: 50000 | F12: 120000 | G12: 250000 | H12: triangular | I12: engineering estimate | J12: Weak | K12: C5 | L12: Labor is ~50% of hPSC manufacturing cost (C5); sized roughly equal to all other per-batch costs. | M12: Derived share, not a measured per-batch figure. | N12: 0.5 | O12: yes
A13: E_facility | B13: Earth: GMP clean-room allocation | C13: USD/batch | D13: Earth | E13: 44000 | F13: 73000 | G13: 110000 | H13: triangular | I13: engineering estimate (derived) | J13: Weak | K13: C5 | L13: Facility upkeep ~$2.2M/yr (C5) / 20-50 batches per year. | M13: Batches/year is judgment. | N13: 0.55 | O13: yes
A14: E_equipment | B14: Earth: bioreactor and equipment allocation | C14: USD/batch | D14: Earth | E14: 5000 | F14: 15000 | G14: 40000 | H14: triangular | I14: engineering estimate | J14: Weak | L14: Stirred-tank bioreactor system amortized over batches. Author estimate. | M14: No source extracted. | N14: 0.4 | O14: yes
A15: E_qc | B15: Earth: release testing | C15: USD/batch | D15: Earth | E15: 10000 | F15: 20000 | G15: 50000 | H15: triangular | I15: measured in target system | J15: Strong | K15: C5 | L15: Outsourced testing ~$10k per lot (C5); more assays for a final cell product. | N15: 0.6 | O15: yes
A16: E_other | B16: Earth: other production cost | C16: USD/batch | D16: Earth | E16: 0 | F16: 0 | G16: 0 | H16: fixed | I16: not extracted | J16: n/a | L16: All costs itemized above. | O16: yes
A17: E_delivery | B17: Earth: delivery cost | C17: USD/batch | D17: Earth | E17: 0 | F17: 0 | G17: 0 | H17: fixed | I17: not extracted | J17: n/a | L17: Not modeled. Earth shipping losses also not modeled. | M17: Slightly favors Earth. | O17: yes
A18: r_g | B18: Space vs Earth: total cells out per input iPSC | C18: ratio | D18: Space | E18: 0.8 | F18: 1.5 | G18: 4 | H18: triangular | I18: measured in another system | J18: Moderate | K18: C6, C7, C9, C10 | L18: 1.5-4x more CMs per input cell under SIMULATED microgravity vs 3D at 1g (C6); much higher proliferation on ISS (C7); low end allows for slowed differentiation (C9, C10). Mode 1.5 = low end of C6 (judgment). | M18: Main evidence is simulated microgravity; real-flight yield per input cell not published. | N18: 0.4 | O18: yes
A19: r_q | B19: Space vs Earth: share of correct heart cells (purity ratio) - THESIS LEVER | C19: ratio | D19: Space | E19: 0.9 | F19: 1.03 | G19: 1.06 | H19: triangular | I19: measured in another system | J19: Moderate | K19: C6, C10, C13 | L19: C6 reports ~99% purity in simulated microgravity; Earth best is ~88-94%, so the ratio can only be ~1.0-1.06 before purity hits 100%. Low end: differentiation inhibited (C10), radiation stress (C13). | M19: Cap: max(q_E) x max(r_q) must be <= 1. A large purity gain is only possible if Earth purity is low. | N19: 0.5 | O19: yes
A20: s | B20: Space: share of good cells surviving return, storage, thaw | C20: fraction | D20: Space | E20: 0.5 | F20: 0.75 | G20: 0.97 | H20: triangular | I20: measured in another system | J20: Moderate | K20: S17, S18, C8 | L20: Post-thaw recovery of cryopreserved stem cells ~68-98% (S17, S18); low 0.5 allows for re-entry stress. | M20: CD34+ data used as proxy; Earth product cryo losses not modeled (favors Earth). | N20: 0.5 | O20: yes
A21: p_S | B21: Space: chance a batch succeeds and is released | C21: probability | D21: Space | E21: 0.5 | F21: 0.8 | G21: 0.95 | H21: triangular | I21: expert judgment | J21: Very weak | K21: C13 | L21: No orbital GMP data. Includes launch delays, hardware faults, contamination, radiation-induced release failures. | M21: SPECULATIVE. | N21: 0.35 | O21: yes
A22: S_cells | B22: Space: starting iPSCs | C22: USD/batch | D22: Space | E22: 1000 | F22: 5000 | G22: 10000 | H22: triangular | I22: measured in target system | J22: Strong | K22: C5 | L22: Same as Earth. | M22: Sampled independently of Earth. | N22: 0.7 | O22: yes
A23: S_consumables | B23: Space: media and consumables flown | C23: USD/batch | D23: Space | E23: 10000 | F23: 40000 | G23: 120000 | H23: triangular | I23: engineering estimate (derived) | J23: Weak | K23: C3 | L23: Same as Earth. | M23: Sampled independently of Earth. | N23: 0.5 | O23: yes
A24: crew_hours | B24: Space: crew time per batch | C24: hours/batch | D24: Space | E24: 0.5 | F24: 3 | G24: 10 | H24: triangular | I24: engineering estimate | J24: Weak | L24: Automated bioreactor; crew installs, swaps media modules, transfers to cold stowage. Author estimate. | M24: SPECULATIVE; full automation could approach zero. | N24: 0.4 | O24: via derived row
A25: crew_rate | B25: Space: ISS crew time price | C25: USD/hour | D25: Space | E25: 130000 | F25: 130000 | G25: 130000 | H25: fixed | I25: measured in target system (price) | J25: Strong | K25: S9 | L25: NASA 2021 full-value commercial pricing. | M25: Policy price; NASA may discount research. | N25: 0.8 | O25: via derived row
A26: S_labor | B26: Space: crew and operations time | C26: USD/batch | D26: Space | E26: =E24*E25 | F26: =F24*F25 | G26: =G24*G25 | H26: triangular | I26: engineering estimate (derived) | J26: Weak | K26: S9 | L26: =crew hours x crew price. | O26: yes
A27: S_facility | B27: Space: orbital lab fee / implementation partner | C27: USD/batch | D27: Space | E27: 50000 | F27: 150000 | G27: 500000 | H27: triangular | I27: speculative scenario | J27: Very weak | L27: No public per-batch price (Space Tango, Redwire, BioServe quote on request). Author placeholder. | M27: SPECULATIVE. | N27: 0.3 | O27: yes
A28: S_equipment | B28: Space: flight bioreactor allocation | C28: USD/batch | D28: Space | E28: 20000 | F28: 75000 | G28: 250000 | H28: triangular | I28: speculative scenario | J28: Very weak | L28: Flight-qualified bioreactor amortized over batches. Author placeholder. | M28: SPECULATIVE. | N28: 0.3 | O28: yes
A29: S_qc | B29: Space: release testing | C29: USD/batch | D29: Space | E29: 10000 | F29: 20000 | G29: 50000 | H29: triangular | I29: measured in target system | J29: Strong | K29: C5 | L29: Same as Earth. | N29: 0.6 | O29: yes
A30: S_other | B30: Space: ground GMP work (pre-flight expansion, post-return processing) | C30: USD/batch | D30: Space | E30: 60000 | F30: 150000 | G30: 300000 | H30: triangular | I30: engineering estimate | J30: Weak | K30: C5 | L30: Ground team still expands iPSCs before flight and processes cells after return (labor + facility share). | M30: Judgment based on Earth labor/facility lines. | N30: 0.45 | O30: yes
A31: L | B31: Launch price to orbital lab | C31: USD/kg | D31: Space | E31: 6500 | F31: 20000 | G31: 71800 | H31: triangular | I31: measured in target system (price) | J31: Strong | K31: S9, S10, S11 | L31: Low: rideshare $6,500/kg (free-flyer orbit); mode: NASA ISS upmass $20,000/kg; high: CRS-2 ~$71,800/kg. | M31: Prices, not costs. | N31: 0.75 | O31: yes
A32: M | B32: Launched mass per batch (hardware share, media, packaging) | C32: kg/batch | D32: Space | E32: 10 | F32: 25 | G32: 60 | H32: triangular | I32: engineering estimate | J32: Weak | L32: ~1e9 iPSCs need ~1 L culture plus several litres of differentiation media over ~2 weeks, plus hardware share. Author estimate. | M32: SPECULATIVE. | N32: 0.4 | O32: yes
A33: ret_mass | B33: Return mass per batch incl. cold stowage | C33: kg/batch | D33: Space | E33: 2 | F33: 5 | G33: 15 | H33: triangular | I33: engineering estimate | J33: Weak | L33: Cryo/cold-stowage container for one batch. Author estimate. | M33: SPECULATIVE. | N33: 0.5 | O33: via derived row
A34: down_rate | B34: Downmass price | C34: USD/kg | D34: Space | E34: 40000 | F34: 40000 | G34: 40000 | H34: fixed | I34: measured in target system (price) | J34: Strong | K34: S9 | L34: NASA 2021 full-value downmass price. | M34: Policy price. | N34: 0.8 | O34: via derived row
A35: C_return | B35: Return and recovery cost | C35: USD/batch | D35: Space | E35: =E33*E34 | F35: =F33*F34 | G35: =G33*G34 | H35: triangular | I35: engineering estimate (derived) | J35: Weak | K35: S9 | L35: =return mass x downmass price. | O35: yes
A36: C_other_del | B36: Other space delivery cost | C36: USD/batch | D36: Space | E36: 0 | F36: 0 | G36: 0 | H36: fixed | I36: not extracted | J36: n/a | L36: Not modeled separately. | O36: yes

Sheet CM_Earth
A1: Team thesis: iPSC-derived heart muscle cells (cardiomyocytes) - Earth: cost and output per attempted batch (point estimates)
A3: Line item | B3: Value | C3: Unit | D3: Note
A4: Earth: starting iPSCs (master cell bank vial) | B4: =CM_Assumptions!$F$10 | C4: USD/batch | D4: measured in target system
A5: Earth: media, growth factors, single-use plastics | B5: =CM_Assumptions!$F$11 | C5: USD/batch | D5: engineering estimate (derived)
A6: Earth: GMP labor | B6: =CM_Assumptions!$F$12 | C6: USD/batch | D6: engineering estimate
A7: Earth: GMP clean-room allocation | B7: =CM_Assumptions!$F$13 | C7: USD/batch | D7: engineering estimate (derived)
A8: Earth: bioreactor and equipment allocation | B8: =CM_Assumptions!$F$14 | C8: USD/batch | D8: engineering estimate
A9: Earth: release testing | B9: =CM_Assumptions!$F$15 | C9: USD/batch | D9: measured in target system
A10: Earth: other production cost | B10: =CM_Assumptions!$F$16 | C10: USD/batch | D10: not extracted
A11: C_E_prod: production cost per batch | B11: =SUM(B4:B10) | C11: USD/batch
A12: Earth delivery cost | B12: =CM_Assumptions!$F$17 | C12: USD/batch
A13: C_E_del: delivered cost per batch | B13: =B11+B12 | C13: USD/batch
A15: N0: starting cells | B15: =CM_Assumptions!$F$6 | C15: cells
A16: g_E: growth (cells out per starting cell) | B16: =CM_Assumptions!$F$7 | C16: fold
A17: q_E: share of correct / qualified cells | B17: =CM_Assumptions!$F$8 | C17: fraction
A18: p_E: batch success probability | B18: =CM_Assumptions!$F$9 | C18: probability
A19: U: cells per unit | B19: =CM_Assumptions!$F$5 | C19: cells/unit
A20: Y_E = N0 x g_E x q_E / U (successful batch) | B20: =B15*B16*B17/B19 | C20: units/batch
A21: Q_E = p_E x Y_E (expected per attempted batch) | B21: =B18*B20 | C21: units/batch
A22: c_E_prod: production cost per unit | B22: =IF(B21>0,B11/B21,"No usable output") | C22: USD/unit
A23: c_E: delivered cost per unit | B23: =IF(B21>0,B13/B21,"No usable output") | C23: USD/unit

Sheet CM_Space
A1: Team thesis: iPSC-derived heart muscle cells (cardiomyocytes) - Space (LEO): cost and output per attempted batch (point estimates)
A3: Line item | B3: Value | C3: Unit | D3: Note
A4: Space: starting iPSCs | B4: =CM_Assumptions!$F$22 | C4: USD/batch | D4: measured in target system
A5: Space: media and consumables flown | B5: =CM_Assumptions!$F$23 | C5: USD/batch | D5: engineering estimate (derived)
A6: Space: crew and operations time | B6: =CM_Assumptions!$F$26 | C6: USD/batch | D6: engineering estimate (derived)
A7: Space: orbital lab fee / implementation partner | B7: =CM_Assumptions!$F$27 | C7: USD/batch | D7: speculative scenario
A8: Space: flight bioreactor allocation | B8: =CM_Assumptions!$F$28 | C8: USD/batch | D8: speculative scenario
A9: Space: release testing | B9: =CM_Assumptions!$F$29 | C9: USD/batch | D9: measured in target system
A10: Space: ground GMP work (pre-flight expansion, post-return processing) | B10: =CM_Assumptions!$F$30 | C10: USD/batch | D10: engineering estimate
A11: C_S_prod: production (orbital manufacturing) cost per batch | B11: =SUM(B4:B10) | C11: USD/batch
A12: L: launch price | B12: =CM_Assumptions!$F$31 | C12: USD/kg
A13: M: launched mass | B13: =CM_Assumptions!$F$32 | C13: kg/batch
A14: C_launch = L x M | B14: =B12*B13 | C14: USD/batch
A15: Return and recovery (return mass x downmass price) | B15: =CM_Assumptions!$F$35 | C15: USD/batch
A16: Other delivery | B16: =CM_Assumptions!$F$36 | C16: USD/batch
A17: C_S_del: delivered cost per batch | B17: =B11+B14+B15+B16 | C17: USD/batch
A19: N0: starting cells (paired with Earth) | B19: =CM_Assumptions!$F$6 | C19: cells
A20: g_E: Earth growth | B20: =CM_Assumptions!$F$7 | C20: fold
A21: r_g: space/Earth growth ratio | B21: =CM_Assumptions!$F$18 | C21: ratio
A22: g_S = g_E x r_g | B22: =B20*B21 | C22: fold
A23: q_E: Earth share of correct cells | B23: =CM_Assumptions!$F$8 | C23: fraction
A24: r_q: space/Earth purity ratio (thesis lever) | B24: =CM_Assumptions!$F$19 | C24: ratio
A25: q_S = q_E x r_q | B25: =B23*B24 | C25: fraction
A26: s: post-return retention | B26: =CM_Assumptions!$F$20 | C26: fraction
A27: p_S: batch success probability | B27: =CM_Assumptions!$F$21 | C27: probability
A28: U: cells per unit | B28: =CM_Assumptions!$F$5 | C28: cells/unit
A29: Y_S_pre = N0 x g_S x q_S / U | B29: =B19*B22*B25/B28 | C29: units/batch
A30: Y_S = Y_S_pre x s | B30: =B29*B26 | C30: units/batch
A31: Q_S_pre = p_S x Y_S_pre | B31: =B27*B29 | C31: units/batch
A32: Q_S = p_S x Y_S (expected delivered per attempted batch) | B32: =B27*B30 | C32: units/batch
A33: c_S_prod: production cost per unit (before transport/return losses) | B33: =IF(B31>0,B11/B31,"No usable output") | C33: USD/unit
A34: c_S: delivered cost per unit | B34: =IF(B32>0,B17/B32,"No usable output") | C34: USD/unit

Sheet CM_Comparison
A1: Team thesis: iPSC-derived heart muscle cells (cardiomyocytes) - comparison and viability (deterministic, point estimates)
A3: Metric | B3: Value | C3: Unit | D3: Note
A4: Earth delivered cost per unit (c_E) | B4: =CM_Earth!B23 | C4: USD/unit
A5: Space delivered cost per unit (c_S) | B5: =CM_Space!B34 | C5: USD/unit
A6: Space production cost per unit (c_S_prod) | B6: =CM_Space!B33 | C6: USD/unit | D6: Includes orbital facility costs; NOT proof of a microgravity effect.
A7: Relative delivered savings = 1 - c_S/c_E | B7: =IF(AND(ISNUMBER(B4),ISNUMBER(B5),B4>0),1-B5/B4,"Not defined") | D7: Negative = space more expensive.
A8: Verdict | B8: =IF(AND(ISNUMBER(B4),ISNUMBER(B5)),IF(B5<B4,"Space cheaper","Earth cheaper or equal"),"See no-output flags")
A10: AT WHAT COSTS IS IT VIABLE? (each line changes one input, others held at point estimates)
A11: Max total space spend per batch to match Earth = c_E x Q_S | B11: =IFERROR(B4*CM_Space!B32,"Not defined") | C11: USD/batch
A12: Max launch price L_max = (c_E x Q_S - C_S_prod - C_return - C_other) / M | B12: =IF(CM_Space!B13>0,(B4*CM_Space!B32-CM_Space!B11-CM_Space!B15-CM_Space!B16)/CM_Space!B13,"Not applicable (M=0)") | C12: USD/kg | D12: Negative = not competitive even with free launch.
A13: Max return cost per batch | B13: =IFERROR(B11-CM_Space!B11-CM_Space!B14-CM_Space!B16,"Not defined") | C13: USD/batch | D13: Negative = not viable even with free return.
A14: Max orbital manufacturing cost per batch (C_S_prod) | B14: =IFERROR(B11-CM_Space!B14-CM_Space!B15-CM_Space!B16,"Not defined") | C14: USD/batch | D14: Negative = not viable even with free manufacturing.
A15: Break-even growth ratio r_g_min = C_S_del x U / (c_E x p_S x N0 x g_E x q_S x s) | B15: =IFERROR(CM_Space!B17*CM_Space!B28/(B4*CM_Space!B27*CM_Space!B19*CM_Space!B20*CM_Space!B25*CM_Space!B26),"Not defined") | C15: ratio
A16: Break-even purity ratio r_q_min = C_S_del x U / (c_E x p_S x N0 x g_S x q_E x s) | B16: =IFERROR(CM_Space!B17*CM_Space!B28/(B4*CM_Space!B27*CM_Space!B19*CM_Space!B22*CM_Space!B23*CM_Space!B26),"Not defined") | C16: ratio | D16: Thesis lever.
A17: Maximum possible purity ratio = 1 / q_E (space purity capped at 100%) | B17: =IFERROR(1/CM_Space!B23,"Not defined") | C17: ratio
A18: Can the purity advantage alone make space viable? | B18: =IF(AND(ISNUMBER(B16),ISNUMBER(B17)),IF(B16<=B17,"Possible in principle","NO: required ratio exceeds the 100%-purity cap"),"Not defined")
A19: Space cost per unit if 100% of space cells were correct | B19: =IFERROR(CM_Space!B17/(CM_Space!B27*CM_Space!B19*CM_Space!B22*CM_Space!B26/CM_Space!B28),"Not defined") | C19: USD/unit | D19: Best case for the thesis.
A20: Required output ratio C_S_del / C_E_del (Q_S/Q_E must exceed this) | B20: =IFERROR(CM_Space!B17/CM_Earth!B13,"Not defined") | C20: ratio
A21: Current output ratio Q_S / Q_E | B21: =IFERROR(CM_Space!B32/CM_Earth!B21,"Not defined") | C21: ratio
A23: P(r_g > r_g_min) under the triangular r_g range, all else fixed | B23: =IF(ISNUMBER(B15),IF(B15<=CM_Assumptions!$E$18,1,IF(B15>=CM_Assumptions!$G$18,0,IF(B15<=CM_Assumptions!$F$18,1-(B15-CM_Assumptions!$E$18)^2/((CM_Assumptions!$G$18-CM_Assumptions!$E$18)*(CM_Assumptions!$F$18-CM_Assumptions!$E$18)),(CM_Assumptions!$G$18-B15)^2/((CM_Assumptions!$G$18-CM_Assumptions!$E$18)*(CM_Assumptions!$G$18-CM_Assumptions!$F$18))))),"Not defined") | C23: probability | D23: Analytic triangular tail. Conditional on the range; not a forecast. Joint uncertainty: run the calculator's Monte Carlo.

Sheet CM_Probabilities
A1: Team thesis: iPSC-derived heart muscle cells (cardiomyocytes) - key assumptions and the author's subjective probability each is true
A2: Subjective judgments drafted from the evidence inventory for discussion; review and replace with your own. NOT derived from p-values, NOT used in the simulation, NOT independent of one another.
A4: ID | B4: Claim | C4: Subjective P(true) | D4: Evidence for | E4: Evidence against | F4: Comment
A5: A1 | B5: Real microgravity yields more correct heart cells per input iPSC than the best Earth 3D bioreactor (r_g x r_q > 1) | C5: 0.35 | D5: C6 (1.5-4x, simulated), C7 (proliferation on ISS) | E5: C9, C10 (differentiation suppressed) | F5: Real-flight yield per input cell not published.
A6: A2 | B6: Purity gain over the best Earth process exceeds 5% (r_q > 1.05) | C6: 0.15 | D6: C6 (~99% purity, simulated) | E6: C2, C3 (Earth already ~90%+) | F6: Math cap: purity cannot exceed 100%.
A7: A3 | B7: Microgravity does not impair the directed differentiation step | C7: 0.45 | D7: C6 | E7: C9, C10 | F7: Thesis needs pluripotency kept AND differentiation to work.
A8: A4 | B8: An orbital batch succeeds and is released at least 80% of the time | C8: 0.35 | E8: C13 (radiation/mutation risk) | F8: No orbital GMP data.
A9: A5 | B9: An orbital bioreactor can run an industrial batch (~1e9 input cells) within 5 years | C9: 0.2 | F9: Current ISS hardware is far smaller.
A10: A6 | B10: Launch to an orbital lab costs <= $20,000/kg for this payload | C10: 0.6 | D10: S9, S10 | E10: S11 | F10: Depends on provider and NASA policy.
A11: A7 | B11: Radiation over a 2-3 week run does not add release-blocking genetic damage | C11: 0.6 | E11: C13 (~5x mutations in HSPC on ISS) | F11: Release testing would catch some.
A13: Product of all P IF independent (they are not; illustration only) | B13: =PRODUCT(C5:C11)
A14: Model-based P(r_g > break-even), from CM_Comparison | B14: =CM_Comparison!B23

Sheet HSC_Assumptions
A1: Blood stem cells: cord-blood CD34+ expansion: assumptions. Point estimate = Most likely. Blue = input, black = formula.
A2: Low/High = range found in (or judged from) the evidence. Subjective confidence = author's probability the true value lies in [Low, High]; not used by the model.
A4: ID | B4: Parameter | C4: Unit | D4: Side | E4: Low | F4: Most likely (point) | G4: High | H4: Distribution | I4: Evidence status | J4: Evidence strength | K4: Source IDs | L4: Basis / derivation | M4: Limitations | N4: Subjective confidence range holds | O4: Used directly by calculator?
A5: U | B5: Cells per reporting unit | C5: cells/unit | D5: Both | E5: 1000000 | F5: 1000000 | G5: 1000000 | H5: fixed | I5: definition | J5: n/a | L5: 1 unit = 1 million functional HSC-equivalent (CD34+) cells. Not a clinical dose. | M5: Accounting choice only. | O5: yes
A6: N0 | B6: Viable starting CD34+ cells per batch (one cord blood unit) | C6: cells | D6: Both | E6: 5000000 | F6: 5000000 | G6: 5000000 | H6: fixed | I6: measured in target system (derived) | J6: Strong | K6: S2 | L6: Derived: ~6.6e8 CD34+ per omidubicel product / 130-fold median expansion = ~5e6 starting CD34+. | M6: Derived arithmetic from snippet values; cord units vary widely. | N6: 0.6 | O6: yes
A7: g_E | B7: Earth gross CD34+ expansion factor | C7: fold | D7: Earth | E7: 35 | F7: 130 | G7: 330 | H7: triangular | I7: measured in target system | J7: Strong | K7: S1, S2, S3 | L7: UM171 ~35-fold (low), omidubicel median 130-fold (mode), SR-1 median 330-fold (high). | M7: Different protocols/products; medians, not long-run means; triangle shape is judgment. | N7: 0.85 | O7: yes
A8: q_E | B8: Earth fraction of expanded CD34+ meeting functional qualification | C8: fraction | D8: Earth | E8: 0.5 | F8: 0.7 | G8: 0.8 | H8: triangular | I8: speculative scenario | J8: Very weak | L8: No post-expansion functional-fraction value was extracted. Placeholder range by author judgment. | M8: NOT EVIDENCE-BASED. Needs an assay definition. | N8: 0.4 | O8: yes
A9: p_E | B9: Earth batch release probability | C9: probability | D9: Earth | E9: 0.88 | F9: 0.96 | G9: 0.99 | H9: triangular | I9: measured in target system | J9: Strong | K9: S1, S4, S8 | L9: SR-1: 2/20 failed release (90%); UM171: 26/27 expanded (96%); CAR-T failure ~4% (other system). | M9: Small samples; failure rates fell as processes matured. | N9: 0.8 | O9: yes
A10: E_cells | B10: Earth: starting material (cord blood unit) | C10: USD/batch | D10: Earth | E10: 30000 | F10: 36000 | G10: 60000 | H10: triangular | I10: measured in another system | J10: Moderate | K10: S7 | L10: Cord blood unit procurement $30k-$60k+; mode near reported ~$36k mean (vendor snippet). | M10: Price years vary; no inflation adjustment. | N10: 0.75 | O10: yes
A11: E_consumables | B11: Earth: media, cytokines, consumables | C11: USD/batch | D11: Earth | E11: 0 | F11: 0 | G11: 0 | H11: fixed | I11: not extracted (included in COGS line) | J11: n/a | K11: S6 | L11: Included in the manufacturing COGS line to avoid double counting; breakdown not extracted. | M11: Breakdown unavailable. | O11: yes
A12: E_labor | B12: Earth: labor | C12: USD/batch | D12: Earth | E12: 0 | F12: 0 | G12: 0 | H12: fixed | I12: not extracted (included in COGS line) | J12: n/a | K12: S6 | L12: Included in the manufacturing COGS line to avoid double counting; breakdown not extracted. | M12: Breakdown unavailable. | O12: yes
A13: E_facility | B13: Earth: GMP facility allocation | C13: USD/batch | D13: Earth | E13: 0 | F13: 0 | G13: 0 | H13: fixed | I13: not extracted (included in COGS line) | J13: n/a | K13: S6 | L13: Included in the manufacturing COGS line to avoid double counting; breakdown not extracted. | M13: Breakdown unavailable. | O13: yes
A14: E_equipment | B14: Earth: equipment allocation | C14: USD/batch | D14: Earth | E14: 0 | F14: 0 | G14: 0 | H14: fixed | I14: not extracted (included in COGS line) | J14: n/a | K14: S6 | L14: Included in the manufacturing COGS line to avoid double counting; breakdown not extracted. | M14: Breakdown unavailable. | O14: yes
A15: E_qc | B15: Earth: quality testing / release | C15: USD/batch | D15: Earth | E15: 0 | F15: 0 | G15: 0 | H15: fixed | I15: not extracted (included in COGS line) | J15: n/a | K15: S6 | L15: Included in the manufacturing COGS line to avoid double counting; breakdown not extracted. | M15: Breakdown unavailable. | O15: yes
A16: E_other | B16: Earth: expansion manufacturing COGS excl. starting material (labor, facility, QC, consumables) | C16: USD/batch | D16: Earth | E16: 40000 | F16: 100000 | G16: 220000 | H16: triangular | I16: measured in another system | J16: Moderate | K16: S5, S6 | L16: Autologous CAR-T COGS ~$96k/dose (S5); reviews cite $170k-220k per batch, projected to fall to $40k-70k. | M16: CAR-T, not HSC expansion; 2019 USD. | N16: 0.6 | O16: yes
A17: E_delivery | B17: Earth: delivery cost | C17: USD/batch | D17: Earth | E17: 0 | F17: 0 | G17: 0 | H17: fixed | I17: not extracted | J17: n/a | L17: Not modeled (courier cost small relative to COGS). Earth shipping losses also not modeled. | M17: Slightly favors Earth. | O17: yes
A18: r_g | B18: Space/Earth gross expansion ratio | C18: ratio | D18: Space | E18: 0.3 | F18: 1 | G18: 2.7 | H18: triangular | I18: measured in another system | J18: Moderate | K18: S12, S13, S14, S16 | L18: Low ~0.33 (sim-microgravity human BM CD34+, no growth vs 3-fold); high ~2.7 (sim-microgravity total cells 11 vs 4.1-fold); mode 1.0 (early ISS HSC work reported comparable growth). Mouse spaceflight shows decreases. | M18: No human cord-blood CD34+ expansion measured in real microgravity under manufacturing conditions. | N18: 0.5 | O18: yes
A19: r_q | B19: Space/Earth qualification-fraction ratio | C19: ratio | D19: Space | E19: 0.15 | F19: 1 | G19: 1.25 | H19: triangular | I19: measured in another system | J19: Moderate | K19: S14, C13 | L19: Low ~0.14 (NOD/SCID repopulation 2.1 vs 14.8 after simulated microgravity); ISS HSPC aging signatures (C13); high 1.25 speculative. | M19: Upper bound speculative. max(q_E) x max(r_q) = 1.0 keeps q_S <= 1. | N19: 0.5 | O19: yes
A20: s | B20: Post-return retention of qualified space output | C20: fraction | D20: Space | E20: 0.5 | F20: 0.75 | G20: 0.97 | H20: triangular | I20: measured in another system | J20: Moderate | K20: S17, S18 | L20: Post-thaw CD34+ recovery: ~98% (S17) down to ~68-74% (S18); low 0.5 allows for re-entry stress. | M20: Earth product cryo/shipping losses not modeled, which favors Earth. | N20: 0.6 | O20: yes
A21: p_S | B21: Space batch release probability | C21: probability | D21: Space | E21: 0.6 | F21: 0.85 | G21: 0.96 | H21: triangular | I21: expert judgment | J21: Very weak | L21: No orbital GMP batch data. Includes launch scrubs, hardware faults, contamination, return delays. Author judgment. | M21: SPECULATIVE. | N21: 0.4 | O21: yes
A22: S_cells | B22: Space: starting material (cord blood unit) | C22: USD/batch | D22: Space | E22: 30000 | F22: 36000 | G22: 60000 | H22: triangular | I22: measured in another system | J22: Moderate | K22: S7 | L22: Same as Earth. | M22: Sampled independently of Earth. | N22: 0.75 | O22: yes
A23: S_consumables | B23: Space: media, cytokines, consumables | C23: USD/batch | D23: Space | E23: 0 | F23: 0 | G23: 0 | H23: fixed | I23: not extracted (included in ground COGS line) | J23: n/a | L23: Included in ground COGS line. | O23: yes
A24: crew_hours | B24: Space: crew time per batch | C24: hours/batch | D24: Space | E24: 0.5 | F24: 2 | G24: 8 | H24: triangular | I24: engineering estimate | J24: Weak | L24: Automated bioreactor payload; crew handles install, sampling and cold-stow transfer. Author estimate. | M24: SPECULATIVE. | N24: 0.5 | O24: via derived row
A25: crew_rate | B25: Space: ISS crew time price | C25: USD/hour | D25: Space | E25: 130000 | F25: 130000 | G25: 130000 | H25: fixed | I25: measured in target system (price) | J25: Strong | K25: S9 | L25: NASA 2021 full-value commercial pricing. | M25: Policy price. | N25: 0.8 | O25: via derived row
A26: S_labor | B26: Space: operations / crew time | C26: USD/batch | D26: Space | E26: =E24*E25 | F26: =F24*F25 | G26: =G24*G25 | H26: triangular | I26: engineering estimate (derived) | J26: Weak | K26: S9 | L26: =crew hours x crew price. | O26: yes
A27: S_facility | B27: Space: orbital facility / implementation-partner allocation | C27: USD/batch | D27: Space | E27: 50000 | F27: 150000 | G27: 500000 | H27: triangular | I27: speculative scenario | J27: Very weak | L27: No public per-batch price. Author placeholder. | M27: SPECULATIVE. | N27: 0.3 | O27: yes
A28: S_equipment | B28: Space: flight hardware allocation | C28: USD/batch | D28: Space | E28: 20000 | F28: 75000 | G28: 250000 | H28: triangular | I28: speculative scenario | J28: Very weak | L28: Flight-qualified bioreactor amortized over expected batches. Author placeholder. | M28: SPECULATIVE. | N28: 0.3 | O28: yes
A29: S_qc | B29: Space: quality testing / release | C29: USD/batch | D29: Space | E29: 0 | F29: 0 | G29: 0 | H29: fixed | I29: not extracted (included in ground COGS line) | J29: n/a | L29: Included in ground COGS line. | O29: yes
A30: S_other | B30: Space: ground GMP processing COGS (pre-flight prep, post-return QC) | C30: USD/batch | D30: Space | E30: 40000 | F30: 100000 | G30: 220000 | H30: triangular | I30: measured in another system | J30: Moderate | K30: S5, S6 | L30: Assumed equal to Earth COGS range. | M30: Sampled independently of Earth COGS. | N30: 0.5 | O30: yes
A31: L | B31: Launch price to LEO station | C31: USD/kg | D31: Space | E31: 6500 | F31: 20000 | G31: 71800 | H31: triangular | I31: measured in target system (price) | J31: Strong | K31: S9, S10, S11 | L31: Low: rideshare $6,500/kg; mode: NASA ISS upmass $20,000/kg; high: CRS-2 ~$71,800/kg. | M31: Prices, not costs. | N31: 0.75 | O31: yes
A32: M | B32: Allocated launched mass per batch | C32: kg/batch | D32: Space | E32: 5 | F32: 15 | G32: 40 | H32: triangular | I32: engineering estimate | J32: Weak | L32: CubeLab-scale bioreactor share + media + cold-chain packaging. Author estimate. | M32: SPECULATIVE. | N32: 0.5 | O32: yes
A33: ret_mass | B33: Return (downmass) per batch incl. cold-stowage | C33: kg/batch | D33: Space | E33: 2 | F33: 5 | G33: 15 | H33: triangular | I33: engineering estimate | J33: Weak | L33: Cryo/cold-stowage container for one batch. Author estimate. | M33: SPECULATIVE. | N33: 0.5 | O33: via derived row
A34: down_rate | B34: Downmass price | C34: USD/kg | D34: Space | E34: 40000 | F34: 40000 | G34: 40000 | H34: fixed | I34: measured in target system (price) | J34: Strong | K34: S9 | L34: NASA 2021 full-value downmass price. | M34: Policy price. | N34: 0.8 | O34: via derived row
A35: C_return | B35: Return and recovery cost | C35: USD/batch | D35: Space | E35: =E33*E34 | F35: =F33*F34 | G35: =G33*G34 | H35: triangular | I35: engineering estimate (derived) | J35: Weak | K35: S9 | L35: =return mass x downmass price. | O35: yes
A36: C_other_del | B36: Other space delivery cost | C36: USD/batch | D36: Space | E36: 0 | F36: 0 | G36: 0 | H36: fixed | I36: not extracted | J36: n/a | L36: Not modeled separately. | O36: yes

Sheet HSC_Earth
A1: Blood stem cells: cord-blood CD34+ expansion - Earth: cost and output per attempted batch (point estimates)
A3: Line item | B3: Value | C3: Unit | D3: Note
A4: Earth: starting material (cord blood unit) | B4: =HSC_Assumptions!$F$10 | C4: USD/batch | D4: measured in another system
A5: Earth: media, cytokines, consumables | B5: =HSC_Assumptions!$F$11 | C5: USD/batch | D5: not extracted (included in COGS line)
A6: Earth: labor | B6: =HSC_Assumptions!$F$12 | C6: USD/batch | D6: not extracted (included in COGS line)
A7: Earth: GMP facility allocation | B7: =HSC_Assumptions!$F$13 | C7: USD/batch | D7: not extracted (included in COGS line)
A8: Earth: equipment allocation | B8: =HSC_Assumptions!$F$14 | C8: USD/batch | D8: not extracted (included in COGS line)
A9: Earth: quality testing / release | B9: =HSC_Assumptions!$F$15 | C9: USD/batch | D9: not extracted (included in COGS line)
A10: Earth: expansion manufacturing COGS excl. starting material (labor, facility, QC, consumables) | B10: =HSC_Assumptions!$F$16 | C10: USD/batch | D10: measured in another system
A11: C_E_prod: production cost per batch | B11: =SUM(B4:B10) | C11: USD/batch
A12: Earth delivery cost | B12: =HSC_Assumptions!$F$17 | C12: USD/batch
A13: C_E_del: delivered cost per batch | B13: =B11+B12 | C13: USD/batch
A15: N0: starting cells | B15: =HSC_Assumptions!$F$6 | C15: cells
A16: g_E: growth (cells out per starting cell) | B16: =HSC_Assumptions!$F$7 | C16: fold
A17: q_E: share of correct / qualified cells | B17: =HSC_Assumptions!$F$8 | C17: fraction
A18: p_E: batch success probability | B18: =HSC_Assumptions!$F$9 | C18: probability
A19: U: cells per unit | B19: =HSC_Assumptions!$F$5 | C19: cells/unit
A20: Y_E = N0 x g_E x q_E / U (successful batch) | B20: =B15*B16*B17/B19 | C20: units/batch
A21: Q_E = p_E x Y_E (expected per attempted batch) | B21: =B18*B20 | C21: units/batch
A22: c_E_prod: production cost per unit | B22: =IF(B21>0,B11/B21,"No usable output") | C22: USD/unit
A23: c_E: delivered cost per unit | B23: =IF(B21>0,B13/B21,"No usable output") | C23: USD/unit

Sheet HSC_Space
A1: Blood stem cells: cord-blood CD34+ expansion - Space (LEO): cost and output per attempted batch (point estimates)
A3: Line item | B3: Value | C3: Unit | D3: Note
A4: Space: starting material (cord blood unit) | B4: =HSC_Assumptions!$F$22 | C4: USD/batch | D4: measured in another system
A5: Space: media, cytokines, consumables | B5: =HSC_Assumptions!$F$23 | C5: USD/batch | D5: not extracted (included in ground COGS line)
A6: Space: operations / crew time | B6: =HSC_Assumptions!$F$26 | C6: USD/batch | D6: engineering estimate (derived)
A7: Space: orbital facility / implementation-partner allocation | B7: =HSC_Assumptions!$F$27 | C7: USD/batch | D7: speculative scenario
A8: Space: flight hardware allocation | B8: =HSC_Assumptions!$F$28 | C8: USD/batch | D8: speculative scenario
A9: Space: quality testing / release | B9: =HSC_Assumptions!$F$29 | C9: USD/batch | D9: not extracted (included in ground COGS line)
A10: Space: ground GMP processing COGS (pre-flight prep, post-return QC) | B10: =HSC_Assumptions!$F$30 | C10: USD/batch | D10: measured in another system
A11: C_S_prod: production (orbital manufacturing) cost per batch | B11: =SUM(B4:B10) | C11: USD/batch
A12: L: launch price | B12: =HSC_Assumptions!$F$31 | C12: USD/kg
A13: M: launched mass | B13: =HSC_Assumptions!$F$32 | C13: kg/batch
A14: C_launch = L x M | B14: =B12*B13 | C14: USD/batch
A15: Return and recovery (return mass x downmass price) | B15: =HSC_Assumptions!$F$35 | C15: USD/batch
A16: Other delivery | B16: =HSC_Assumptions!$F$36 | C16: USD/batch
A17: C_S_del: delivered cost per batch | B17: =B11+B14+B15+B16 | C17: USD/batch
A19: N0: starting cells (paired with Earth) | B19: =HSC_Assumptions!$F$6 | C19: cells
A20: g_E: Earth growth | B20: =HSC_Assumptions!$F$7 | C20: fold
A21: r_g: space/Earth growth ratio | B21: =HSC_Assumptions!$F$18 | C21: ratio
A22: g_S = g_E x r_g | B22: =B20*B21 | C22: fold
A23: q_E: Earth share of correct cells | B23: =HSC_Assumptions!$F$8 | C23: fraction
A24: r_q: space/Earth purity ratio (thesis lever) | B24: =HSC_Assumptions!$F$19 | C24: ratio
A25: q_S = q_E x r_q | B25: =B23*B24 | C25: fraction
A26: s: post-return retention | B26: =HSC_Assumptions!$F$20 | C26: fraction
A27: p_S: batch success probability | B27: =HSC_Assumptions!$F$21 | C27: probability
A28: U: cells per unit | B28: =HSC_Assumptions!$F$5 | C28: cells/unit
A29: Y_S_pre = N0 x g_S x q_S / U | B29: =B19*B22*B25/B28 | C29: units/batch
A30: Y_S = Y_S_pre x s | B30: =B29*B26 | C30: units/batch
A31: Q_S_pre = p_S x Y_S_pre | B31: =B27*B29 | C31: units/batch
A32: Q_S = p_S x Y_S (expected delivered per attempted batch) | B32: =B27*B30 | C32: units/batch
A33: c_S_prod: production cost per unit (before transport/return losses) | B33: =IF(B31>0,B11/B31,"No usable output") | C33: USD/unit
A34: c_S: delivered cost per unit | B34: =IF(B32>0,B17/B32,"No usable output") | C34: USD/unit

Sheet HSC_Comparison
A1: Blood stem cells: cord-blood CD34+ expansion - comparison and viability (deterministic, point estimates)
A3: Metric | B3: Value | C3: Unit | D3: Note
A4: Earth delivered cost per unit (c_E) | B4: =HSC_Earth!B23 | C4: USD/unit
A5: Space delivered cost per unit (c_S) | B5: =HSC_Space!B34 | C5: USD/unit
A6: Space production cost per unit (c_S_prod) | B6: =HSC_Space!B33 | C6: USD/unit | D6: Includes orbital facility costs; NOT proof of a microgravity effect.
A7: Relative delivered savings = 1 - c_S/c_E | B7: =IF(AND(ISNUMBER(B4),ISNUMBER(B5),B4>0),1-B5/B4,"Not defined") | D7: Negative = space more expensive.
A8: Verdict | B8: =IF(AND(ISNUMBER(B4),ISNUMBER(B5)),IF(B5<B4,"Space cheaper","Earth cheaper or equal"),"See no-output flags")
A10: AT WHAT COSTS IS IT VIABLE? (each line changes one input, others held at point estimates)
A11: Max total space spend per batch to match Earth = c_E x Q_S | B11: =IFERROR(B4*HSC_Space!B32,"Not defined") | C11: USD/batch
A12: Max launch price L_max = (c_E x Q_S - C_S_prod - C_return - C_other) / M | B12: =IF(HSC_Space!B13>0,(B4*HSC_Space!B32-HSC_Space!B11-HSC_Space!B15-HSC_Space!B16)/HSC_Space!B13,"Not applicable (M=0)") | C12: USD/kg | D12: Negative = not competitive even with free launch.
A13: Max return cost per batch | B13: =IFERROR(B11-HSC_Space!B11-HSC_Space!B14-HSC_Space!B16,"Not defined") | C13: USD/batch | D13: Negative = not viable even with free return.
A14: Max orbital manufacturing cost per batch (C_S_prod) | B14: =IFERROR(B11-HSC_Space!B14-HSC_Space!B15-HSC_Space!B16,"Not defined") | C14: USD/batch | D14: Negative = not viable even with free manufacturing.
A15: Break-even growth ratio r_g_min = C_S_del x U / (c_E x p_S x N0 x g_E x q_S x s) | B15: =IFERROR(HSC_Space!B17*HSC_Space!B28/(B4*HSC_Space!B27*HSC_Space!B19*HSC_Space!B20*HSC_Space!B25*HSC_Space!B26),"Not defined") | C15: ratio
A16: Break-even purity ratio r_q_min = C_S_del x U / (c_E x p_S x N0 x g_S x q_E x s) | B16: =IFERROR(HSC_Space!B17*HSC_Space!B28/(B4*HSC_Space!B27*HSC_Space!B19*HSC_Space!B22*HSC_Space!B23*HSC_Space!B26),"Not defined") | C16: ratio | D16: Thesis lever.
A17: Maximum possible purity ratio = 1 / q_E (space purity capped at 100%) | B17: =IFERROR(1/HSC_Space!B23,"Not defined") | C17: ratio
A18: Can the purity advantage alone make space viable? | B18: =IF(AND(ISNUMBER(B16),ISNUMBER(B17)),IF(B16<=B17,"Possible in principle","NO: required ratio exceeds the 100%-purity cap"),"Not defined")
A19: Space cost per unit if 100% of space cells were correct | B19: =IFERROR(HSC_Space!B17/(HSC_Space!B27*HSC_Space!B19*HSC_Space!B22*HSC_Space!B26/HSC_Space!B28),"Not defined") | C19: USD/unit | D19: Best case for the thesis.
A20: Required output ratio C_S_del / C_E_del (Q_S/Q_E must exceed this) | B20: =IFERROR(HSC_Space!B17/HSC_Earth!B13,"Not defined") | C20: ratio
A21: Current output ratio Q_S / Q_E | B21: =IFERROR(HSC_Space!B32/HSC_Earth!B21,"Not defined") | C21: ratio
A23: P(r_g > r_g_min) under the triangular r_g range, all else fixed | B23: =IF(ISNUMBER(B15),IF(B15<=HSC_Assumptions!$E$18,1,IF(B15>=HSC_Assumptions!$G$18,0,IF(B15<=HSC_Assumptions!$F$18,1-(B15-HSC_Assumptions!$E$18)^2/((HSC_Assumptions!$G$18-HSC_Assumptions!$E$18)*(HSC_Assumptions!$F$18-HSC_Assumptions!$E$18)),(HSC_Assumptions!$G$18-B15)^2/((HSC_Assumptions!$G$18-HSC_Assumptions!$E$18)*(HSC_Assumptions!$G$18-HSC_Assumptions!$F$18))))),"Not defined") | C23: probability | D23: Analytic triangular tail. Conditional on the range; not a forecast. Joint uncertainty: run the calculator's Monte Carlo.

Sheet HSC_Probabilities
A1: Blood stem cells: cord-blood CD34+ expansion - key assumptions and the author's subjective probability each is true
A2: Subjective judgments drafted from the evidence inventory for discussion; review and replace with your own. NOT derived from p-values, NOT used in the simulation, NOT independent of one another.
A4: ID | B4: Claim | C4: Subjective P(true) | D4: Evidence for | E4: Evidence against | F4: Comment
A5: A1 | B5: Real microgravity increases gross expansion of human cord-blood CD34+ cells vs matched Earth controls (r_g > 1) | C5: 0.3 | D5: S14 (sim. microgravity, more cells at day 5) | E5: S12, S13 (decreased proliferation), C13 | F5: Mixed evidence; mostly simulated microgravity or mouse cells.
A6: A2 | B6: Microgravity-expanded cells keep Earth-equivalent function (r_q >= 1) | C6: 0.25 | D6: None direct | E6: S14 (repopulation 2.1 vs 14.8), C13 (ISS aging signatures) | F6: Functional data point the other way.
A7: A3 | B7: Earth CD34+ expansion of ~35-330 fold is achievable at GMP scale | C7: 0.85 | D7: S1, S2, S3 | F7: Approved product (Omisirge) exists.
A8: A4 | B8: Orbital batch release probability >= 85% | C8: 0.35 | E8: No orbital GMP data | F8: Pure judgment.
A9: A5 | B9: Launch to an orbital lab at <= $20,000/kg is available for this payload class | C9: 0.6 | D9: S9, S10 | E9: S11 | F9: Depends on provider and NASA policy.
A10: A6 | B10: Post-return retention of qualified cells >= 75% | C10: 0.5 | D10: S17 | E10: S18 | F10: Cryo recovery data from Earth shipping, not re-entry.
A11: A7 | B11: Space-specific overheads (facility, hardware, crew) <= $300k per batch at the point estimate | C11: 0.4 | F11: No public prices; placeholders.
A13: Product of all P IF independent (they are not; illustration only) | B13: =PRODUCT(C5:C11)
A14: Model-based P(r_g > break-even), from HSC_Comparison | B14: =HSC_Comparison!B23

Sheet PRD_Check
A1: PRD section 11 check case (hypothetical inputs; verifies the formulas)
A3: Item | B3: Value | C3: Unit | D3: Note
A4: U | B4: 1000000
A5: N0 | B5: 1000000
A6: g_E | B6: 20
A7: r_g | B7: 2
A8: q_E | B8: 0.5
A9: r_q | B9: 1
A10: s | B10: 0.8
A11: p_E | B11: 1
A12: p_S | B12: 1
A13: C_E_prod | B13: 100000
A14: E_delivery | B14: 0
A15: C_S_prod | B15: 200000
... A19: C_other | B19: 0
A20: Earth output Y_E (expect 10) | B20: =B5*B6*B8/B4
A21: Space pre-return output (expect 20) | B21: =B5*B6*B7*B8*B9/B4
A22: Space delivered output (expect 16) | B22: =B21*B10
A23: Earth delivered cost (expect $10,000) | B23: =(B13+B14)/(B11*B20)
A24: Space production cost (expect $10,000) | B24: =B15/(B12*B21)
A25: C_S_del (expect $350,000) | B25: =B15+B16*B17+B18+B19
A26: Space delivered cost (expect $21,875) | B26: =B25/(B12*B22)
A27: Savings (expect -118.75%) | B27: =1-B26/B23
A28: r_g_min (expect 4.375) | B28: =B25*B4/(B23*B12*B5*B6*B8*B9*B10)
A29: L_max (expect -$1,800/kg) | B29: =(B23*B12*B22-B15-B18-B19)/B17
A30: P(r_g > 4.375) for triangular(1,2,6) (expect 13.203125%) | B30: =(6-4.375)^2/((6-1)*(6-2))

Sheet Sources
A1: Sources (inventory, not votes). Verification: READ = page opened; SNIPPET = search summary only.
A3: ID | B3: Title | C3: Year | D3: URL | E3: Verification | F3: System | G3: Side | H3: Extracted finding | I3: Direction | J3: Linked inputs
A4: C1 | B4: Kempf H et al. Controlling Expansion and Cardiomyogenic Differentiation of Human Pluripotent Stem Cells in Scalable Suspension Culture. Stem Cell Reports | C4: 2014 | D4: https://pmc.ncbi.nlm.nih.gov/articles/PMC4264033/ | E4: READ | F4: Human iPSC/ESC, stirred-tank bioreactor (Earth, 3D) | G4: Earth | H4: Bioreactor CM purity: HES3 68.6% +/- 8.7%; iPSC line 58% +/- 30.3% (runs 27-88%); ~40 million CMs per run; all 3 runs from batch-expanded cells failed. | I4: supportive (Earth baseline; shows variability) | J4: q_E, p_E
A5: C2 | B5: Halloin C et al. Continuous WNT Control Enables Advanced hPSC Cardiac Processing and Prognostic Surface Marker Identification in Chemically Defined Suspension Culture. Stem Cell Reports | C5: 2019 | D5: https://pmc.ncbi.nlm.nih.gov/articles/PMC6700605/ | E5: READ | F5: Human PSC, suspension bioreactor (Earth, 3D) | G5: Earth | H5: 93.5% +/- 5.0% cTnT+ at 150 ml (n=3); 89.1% +/- 7.8% at 350-500 ml; up to ~4-4.5e8 CMs per run. | I5: supportive (Earth best case) | J5: q_E, g_E
A6: C3 | B6: Prondzynski M et al. Efficient and reproducible generation of human iPSC-derived cardiomyocytes in stirred suspension (bioRxiv 2024; Nat Commun 2024) | C6: 2024 | D6: https://pmc.ncbi.nlm.nih.gov/articles/PMC10925150/ | E6: READ | F6: Human iPSC, 19 bioreactor runs, 10 lines (Earth, 3D) | G6: Earth | H6: >90% cTnT+; ~2.5 CMs per input iPSC; ~$569 materials per run of ~124M CMs (research grade, excl. labor) vs ~$1,075 monolayer. | I6: supportive (Earth baseline) | J6: g_E, q_E, E_consumables
A7: C4 | B7: Chemically defined cardiomyocyte differentiation protocol (STAR Protocols) | C7: 2020 | D7: https://www.cell.com/star-protocols/fulltext/S2666-1667(20)30002-2 | E7: SNIPPET | F7: Human iPSC, hundreds of batches, >50 lines | G7: Earth | H7: Successful differentiation (>85% purity) in over 80% of runs. | I7: supportive (run success rate) | J7: p_E
A8: C5 | B8: Kim JH, Kawase E, Bharti K, Karnieli O, Arakawa Y, Stacey G. Perspectives on the cost of goods for hPSC banks for manufacture of cell therapies. npj Regenerative Medicine 7:54 | C8: 2022 | D8: https://pmc.ncbi.nlm.nih.gov/articles/PMC9522845/ | E8: READ | F8: GMP hPSC banking | G8: Earth | H8: 300-vial bank ~$300,000 (~$1,000/vial; range $1,000-10,000 across banks); labor ~50% of cost; outsourced testing ~$10k/lot; facility upkeep ~$2.2M/yr. | I8: supportive (cost) | J8: E_cells, E_labor, E_facility, E_qc
A9: C6 | B9: Jha R, Wu Q, Singh M et al. Simulated Microgravity and 3D Culture Enhance Induction, Viability, Proliferation and Differentiation of Cardiac Progenitors from Human Pluripotent Stem Cells. Scientific Reports 6:30956 | C9: 2016 | D9: https://www.nature.com/articles/srep30956 | E9: SNIPPET | F9: Human PSC, random positioning machine vs 3D at 1g | G9: Space | H9: ~99% CM purity, ~90% viability, 1.5-4-fold more CMs per input stem cell vs 3D culture at normal gravity. | I9: supportive (simulated microgravity) | J9: r_g, r_q
A10: C7 | B10: Rampoldi A et al. Space microgravity improves proliferation of human iPSC-derived cardiomyocytes. Stem Cell Reports 17:2272 | C10: 2022 | D10: https://www.cell.com/stem-cell-reports/fulltext/S2213-6711(22)00416-7 | E10: SNIPPET | F10: Human iPSC cardiac progenitors, ISS 3 weeks | G10: Space | H10: Spheres ~3x larger, ~20x more nuclei than 1g controls; higher proliferation; better calcium handling. No purity comparison seen. | I10: supportive (real spaceflight) | J10: r_g
A11: C8 | B11: Wnorowski A, Sharma A et al. Effects of Spaceflight on Human Induced Pluripotent Stem Cell-Derived Cardiomyocyte Structure and Function. Stem Cell Reports | C11: 2019 | D11: https://www.cell.com/stem-cell-reports/fulltext/S2213-6711(19)30367-4 | E11: SNIPPET | F11: Human iPSC-CMs, ISS ~5.5 weeks | G11: Space | H11: 2,635 differentially expressed genes; altered calcium handling; structure unchanged; reverted after return. Says nothing about yield. | I11: contextual | J11: s
A12: C9 | B12: Timilsina S et al. Enhanced self-renewal of human pluripotent stem cells by simulated microgravity. npj Microgravity 8:22 | C12: 2022 | D12: https://pmc.ncbi.nlm.nih.gov/articles/PMC9253108/ | E12: READ | F12: Human PSC, 2D clinostat vs adherent 1g (no 3D control) | G12: Space | H12: Pluripotency genes up >2-fold, more cells, less induced differentiation. Supports 'stays pluripotent'; may also slow directed differentiation. | I12: mixed | J12: r_g, r_q
A13: C10 | B13: Blaber EA et al. Microgravity Reduces the Differentiation and Regenerative Potential of Embryonic Stem Cells. Stem Cells and Development 24:2605 | C13: 2015 | D13: https://pmc.ncbi.nlm.nih.gov/articles/PMC4652210/ | E13: SNIPPET | F13: Mouse ESC, 15 days actual spaceflight | G13: Space | H13: Differentiation inhibited across germ layers; stemness retained. | I13: mixed (supports pluripotency, against differentiation) | J13: r_g, r_q
A14: C11 | B14: Heartseed HS-001 dosing (Nikon press release) | C14: 2025 | D14: https://www.nikon.com/company/news/2025/0203_01/ | E14: SNIPPET | F14: iPSC-CM clinical product | G14: Earth | H14: 50 million (low) and 150 million (high) cardiomyocytes per patient. | I14: contextual (dose size) | J14: none (context)
A15: C12 | B15: Ncardia large-scale hiPSC-cardiomyocyte manufacturing (Axion application note) | C15: not extracted | D15: https://www.axionbiosystems.com/resources/application-note/controlled-large-scale-manufacturing-hipsc-derived-cardiomyocytes | E15: SNIPPET | F15: Industrial iPSC-CM batch | G15: Earth | H15: 7.5e9 cells at 87% cTnT+ in one batch. | I15: supportive (scale) | J15: N0, q_E
A16: C13 | B16: Nanobioreactor detection of space-associated hematopoietic stem and progenitor cell aging. Cell Stem Cell (Jamieson lab) | C16: 2025 | D16: https://www.cell.com/cell-stem-cell/fulltext/S1934-5909(25)00270-X | E16: SNIPPET | F16: Human HSPC, ISS 32-45 days | G16: Space | H16: Aging signatures and ~5x more mutations than ground controls: a radiation/stress risk for any stem-cell product. | I16: contradictory (risk) | J16: p_S, r_q
A17: C14 | B17: Phipson B et al. Evaluation of variability in human kidney organoids. Nature Methods 16:79 | C17: 2019 | D17: https://pmc.ncbi.nlm.nih.gov/articles/PMC6634992/ | E17: SNIPPET | F17: Human iPSC kidney organoids | G17: Earth | H17: Batch (not clone) is the main source of variation. Kidney differentiation is less controlled than cardiac: a stronger case for a quality lever. | I17: contextual (kidney) | J17: none (context)
A18: P1 | B18: SpaceOrbitals: How Cheap Is Starship V3 Really? A Plain-English Look at the 2026 $/kg-to-LEO Math | C18: 2026 | D18: https://spaceorbitals.com/articles/starship-v3-cost-per-kg-2026/ | E18: READ | F18: Launch price projection (secondary source) | G18: Space | H18: Starship target '<$200/kg' (SpaceX since 2019); Musk May 2026: '$100-200 per kg' fully reusable (aspirational); '$500-1,000 (realistic mid-decade)'. No published Starship price. | I18: projection | J18: L
A19: P2 | B19: Payload Space: Varda Conducts First Reentry Mission into Australia | C19: 2025 | D19: https://payloadspace.com/varda-conducts-first-reentry-mission-into-australia/ | E19: READ | F19: Free-flyer reentry capsule (Varda) | G19: Space | H19: AFRL's Capt. Ashwin Rao: Varda 'reduces the cost of a reentry flight test from on the order of $100M to around $5M.' Capsule capacity not stated. | I19: projection | J19: C_return, S_facility
A20: S1 | B20: Wagner JE et al. Phase I/II Trial of StemRegenin-1 Expanded Umbilical Cord Blood Hematopoietic Stem Cells Supports Testing as a Stand-Alone Graft. Cell Stem Cell | C20: 2016 | D20: https://pmc.ncbi.nlm.nih.gov/articles/PMC4881386/ | E20: READ | F20: Human cord blood CD34+, GMP clinical | G20: Earth | H20: CD34+ median 330-fold expansion (range 67-848); TNC 854-fold; 15-day culture. 2 of 20 products failed lot release; later 13 all passed. | I20: supportive (Earth baseline) | J20: g_E, p_E
A21: S2 | B21: Horwitz ME et al. Omidubicel vs standard myeloablative umbilical cord blood transplantation: phase 3 randomized study. Blood 138(16):1429 | C21: 2021 | D21: https://ashpublications.org/blood/article/138/16/1429/476235/ | E21: SNIPPET | F21: Human cord blood CD34+, approved product (Omisirge) | G21: Earth | H21: CD34+ median 130-fold (32-233); ~6.6e8 CD34+ per product. | I21: supportive (Earth baseline) | J21: g_E, N0
A22: S3 | B22: Single UM171 expanded cord blood transplant is feasible and safe. Experimental Hematology | C22: 2017 | D22: https://www.exphem.org/article/S0301-472X(17)30299-0/fulltext | E22: SNIPPET | F22: Human cord blood CD34+ | G22: Earth | H22: CD34+ median net 35-fold expansion (n=7). | I22: supportive (Earth baseline) | J22: g_E
A23: S4 | B23: Cohen S et al. Hematopoietic stem cell transplantation using single UM171-expanded cord blood: phase 1-2 study. Lancet Haematology | C23: 2019 | D23: https://www.thelancet.com/journals/lanhae/article/PIIS2352-3026(19)30202-9/abstract | E23: SNIPPET | F23: Human cord blood CD34+ | G23: Earth | H23: 26 of 27 units expanded successfully (96%). | I23: supportive (Earth baseline) | J23: p_E
A24: S5 | B24: Harrison RP, Zylberberg E, Ellison S, Levine BL. CAR-T cell therapy manufacturing: modelling the effect of offshore production on aggregate cost of goods. Cytotherapy 21(2):224-233 | C24: 2019 | D24: https://www.sciencedirect.com/science/article/pii/S1465324919300039 | E24: SNIPPET | F24: CAR-T (different cell product) | G24: Earth | H24: Autologous COGS ~$95,780 per dose; allogeneic ~$4,460 per dose (2019 USD, not inflation-adjusted). | I24: contextual (other system) | J24: E_other, S_other
A25: S6 | B25: ten Ham RMT et al. What does cell therapy manufacturing cost? A framework and methodology. Cytotherapy 22(7):388-397 | C25: 2020 | D25: https://www.isct-cytotherapy.org/article/S1465-3249(20)30496-5/fulltext | E25: SNIPPET | F25: Academic cell-therapy facilities (EU) | G25: Earth | H25: Costing framework (fixed vs variable per-batch costs, 2018 EUR, 5% failure assumption). Per-batch totals not extracted. | I25: contextual (method) | J25: E_* cost structure
A26: S7 | B26: HRSA Advisory Council on Blood Stem Cell Transplantation: Access to transplantation (Champlin R., slides) | C26: not extracted | D26: https://bloodstemcell.hrsa.gov/sites/default/files/bloodstemcell/about/advisory-council/meetings/access-to-transplantation.pdf | E26: SNIPPET | F26: Unrelated cord blood unit procurement | G26: Earth | H26: Cord blood unit procurement ~$30,000-$60,000+. | I26: supportive (cost) | J26: E_cells, S_cells
A27: S8 | B27: UK National CAR T Clinical Panel: manufacturing failure analysis. Blood Cancer Journal | C27: 2025 | D27: https://www.nature.com/articles/s41408-025-01225-9 | E27: SNIPPET | F27: CAR-T (different cell product) | G27: Earth | H27: LBCL manufacturing failure 3.87% (38/981). | I27: contextual (other system) | J27: p_E
A28: S9 | B28: NASA ISS Updated Commercial and Marketing Pricing Policy (summary on eoPortal) | C28: 2021 | D28: https://www.eoportal.org/ftp/satellite-missions/iss/ISS-Pricing-08032021/ISS-Pricing.html | E28: READ | F28: ISS commercial access | G28: Space | H28: 2021 full-value pricing: upmass $20,000/kg, downmass $40,000/kg, crew time $130,000/hour (2019 policy: $3,000/kg, $6,000/kg, $17,500/hr). | I28: supportive (cost) | J28: L, crew_rate, down_rate
A29: S10 | B29: Payload Space: SpaceX Increases Rideshare Prices | C29: 2025 | D29: https://payloadspace.com/spacex-increases-rideshare-prices/ | E29: SNIPPET | F29: Falcon 9 Transporter rideshare to SSO | G29: Space | H29: Rideshare $6,500/kg (2025), $7,000/kg (2026). Free-flyer orbit, not ISS delivery. | I29: contextual (cost floor) | J29: L
A30: S11 | B30: NASA Office of Inspector General IG-18-016: NASA's Management of Commercial Resupply Services Contracts | C30: 2018 | D30: https://oig.nasa.gov/docs/IG-18-016.pdf | E30: SNIPPET | F30: ISS commercial cargo (CRS) | G30: Space | H30: Estimated SpaceX cargo cost ~$63,200/kg (CRS-1), ~$71,800/kg projected (CRS-2), as reported by secondary sources. | I30: supportive (cost ceiling) | J30: L
A31: S12 | B31: Wang P et al. Spaceflight/microgravity inhibits the proliferation of hematopoietic stem cells by decreasing Kit-Ras/cAMP-CREB pathway networks. FASEB J 33(5):5903 | C31: 2019 | D31: https://pmc.ncbi.nlm.nih.gov/articles/PMC6463920/ | E31: READ | F31: Mouse bone-marrow Lin- HSPC; actual spaceflight + RWV | G31: Space | H31: Reduced HSPC proliferation, G0/G1 arrest; differentiation not changed. No fold magnitude stated. | I31: contradictory | J31: r_g
A32: S13 | B32: Proliferation of human hematopoietic bone marrow cells in simulated microgravity (PubMed 11332740) | C32: not extracted | D32: https://pubmed.ncbi.nlm.nih.gov/11332740/ | E32: SNIPPET | F32: Human bone-marrow CD34+; simulated microgravity | G32: Space | H32: Normal-gravity cells grew up to ~3-fold by day 4-6; simulated-microgravity cells did not increase (ratio ~0.33). | I32: contradictory | J32: r_g
A33: S14 | B33: Proliferation and functional characterization of human CD34+ bone marrow cells cultured in simulated microgravity. Experimental Hematology | C33: not extracted | D33: https://www.sciencedirect.com/science/article/abs/pii/S0301472X00003921 | E33: SNIPPET | F33: Human CD34+; simulated microgravity (RWV) | G33: Space | H33: Day 5 total cells 11 vs 4.1-fold (ratio ~2.7); CD34+ 2.6 vs 1.0; but NOD/SCID repopulation 2.1 vs 14.8 (worse function, ratio ~0.14). | I33: mixed | J33: r_g, r_q
A34: S16 | B34: NASA: Growing Stem Cells in Space to Improve Cancer and Disease Treatments (InSPA StemCellEX-H2) | C34: 2026 | D34: https://www.nasa.gov/missions/station/iss-research/growing-stem-cells-in-space-to-improve-cancer-and-disease-treatments/ | E34: SNIPPET | F34: Human cord blood CD34+ expansion on ISS | G34: Space | H34: Target-system expansion experiment; no published yield results as of research date. | I34: contextual (pending) | J34: r_g
A35: S17 | B35: Fisher V et al. Analysis of the Recovery of Cryopreserved and Thawed CD34+ and CD3+ Cells Collected for Hematopoietic Transplantation. Transfusion | C35: 2014 | D35: https://pmc.ncbi.nlm.nih.gov/articles/PMC3983171/ | E35: READ | F35: Human mobilized CD34+, cryopreserved | G35: Space | H35: CD34+ recovery 97.5% (related, n=86) and 98.8% (unrelated, n=14); total-cell viability 64-79%. | I35: supportive (retention ceiling) | J35: s
A36: S18 | B36: Post-thaw recovery of cryopreserved leukapheresis products (PubMed 37460360) | C36: not extracted | D36: https://pubmed.ncbi.nlm.nih.gov/37460360/ | E36: SNIPPET | F36: Human apheresis CD34+, cryopreserved | G36: Space | H36: Median viable CD34+ recovery 73.7% autologous, 68.1% allogeneic. | I36: supportive (retention) | J36: s
A37: S19 | B37: ACA Pharma: Omisirge WAC price (citing Gamida Cell order sheet) | C37: 2026 | D37: https://acapharma.net/omisirge-wac-price/ | E37: SNIPPET | F37: Omidubicel list price (distributor page) | G37: Earth | H37: WAC $693,900 per treatment. Price, not cost; context only. | I37: contextual (price) | J37: none (context)
